setup.py
Products/__init__.py
Products.ForumPage.egg-info/PKG-INFO
Products.ForumPage.egg-info/SOURCES.txt
Products.ForumPage.egg-info/dependency_links.txt
Products.ForumPage.egg-info/entry_points.txt
Products.ForumPage.egg-info/namespace_packages.txt
Products.ForumPage.egg-info/not-zip-safe
Products.ForumPage.egg-info/requires.txt
Products.ForumPage.egg-info/top_level.txt
Products/ForumPage/__init__.py
Products/ForumPage/changes.txt
Products/ForumPage/config.py
Products/ForumPage/configure.zcml
Products/ForumPage/profiles.zcml
Products/ForumPage/readme.txt
Products/ForumPage/refresh.txt
Products/ForumPage/setuphandlers.py
Products/ForumPage/version.txt
Products/ForumPage/_darcs/inventory
Products/ForumPage/_darcs/patches/20100320210659-422b6-30d4a29733af8eaa28fa978c085b25b100de301c.gz
Products/ForumPage/_darcs/patches/20100321123429-422b6-6e8cddbd1e540220bf5796e1aff159f5e50313ac.gz
Products/ForumPage/_darcs/patches/20100321211606-422b6-d667ffc4f1a66ae5b89772047f4fc6bbc5c58641.gz
Products/ForumPage/_darcs/patches/pending
Products/ForumPage/_darcs/prefs/author
Products/ForumPage/_darcs/prefs/binaries
Products/ForumPage/_darcs/prefs/boring
Products/ForumPage/_darcs/prefs/defaultrepo
Products/ForumPage/_darcs/prefs/motd
Products/ForumPage/_darcs/prefs/repos
Products/ForumPage/_darcs/pristine/README.txt
Products/ForumPage/_darcs/pristine/__init__.py
Products/ForumPage/_darcs/pristine/config.py
Products/ForumPage/_darcs/pristine/configure.zcml
Products/ForumPage/_darcs/pristine/profiles.zcml
Products/ForumPage/_darcs/pristine/refresh.txt
Products/ForumPage/_darcs/pristine/setuphandlers.py
Products/ForumPage/_darcs/pristine/version.txt
Products/ForumPage/_darcs/pristine/content/ForumPage.py
Products/ForumPage/_darcs/pristine/content/__init__.py
Products/ForumPage/_darcs/pristine/content/interfaces.py
Products/ForumPage/_darcs/pristine/content/utilities.py
Products/ForumPage/_darcs/pristine/i18n/forumpage-no.po
Products/ForumPage/_darcs/pristine/profiles/default/ForumPage_marker.txt
Products/ForumPage/_darcs/pristine/profiles/default/cssregistry.xml
Products/ForumPage/_darcs/pristine/profiles/default/factorytool.xml
Products/ForumPage/_darcs/pristine/profiles/default/import_steps.xml
Products/ForumPage/_darcs/pristine/profiles/default/jsregistry.xml
Products/ForumPage/_darcs/pristine/profiles/default/skins.xml
