Metadata-Version: 1.0
Name: Products.ForumPage
Version: 1.0.3
Summary: A content-type that lists Ploneboard forums and their posts
Home-page: http://www.nidelven-it.no/d
Author: Morten W. Petersen
Author-email: info@nidelven-it.no
License: GPL
Keywords: python plone ploneboard presentation
Platform: UNKNOWN
Classifier: Programming Language :: Python
Classifier: Framework :: Zope2
Classifier: Framework :: Plone
